form_observability/__init__.py
form_observability/conftest.py
form_observability/context_aware.py
form_observability/log.py
form_observability/otel_value.py
form_observability/pipeline_setup.py
form_observability/test_context_aware.py
form_observability/testing.py
form_observability/dagster_otel/__init__.py
form_observability/dagster_otel/otel_ops.py
form_observability/dagster_otel/test_otel_op.py
form_observability/dagster_otel/test_timing.py
form_observability/dagster_otel/testing.py
form_observability/dagster_otel/timing.py
form_observability/dagster_otel/util.py
formenergy_observability-0.3.2.dist-info/LICENSE
formenergy_observability-0.3.2.dist-info/WHEEL
formenergy_observability-0.3.2.dist-info/METADATA
formenergy_observability-0.3.2.dist-info/RECORD
