Metadata-Version: 2.1
Name: formenergy-observability
Version: 0.3.2
Summary: OTel tracing/logging tools, emphasizing data pipeline use cases with Dagster.
Author-email: Form Energy Software <software@formenergy.com>
Requires-Python: >=3.8
Classifier: Programming Language :: Python :: 3
Classifier: License :: OSI Approved :: MIT License
Classifier: Operating System :: OS Independent
Requires-Dist: grpcio>=1.48.1
Requires-Dist: packaging>=20.9,<22
Requires-Dist: dagster>=1.5.0,<2
Requires-Dist: opentelemetry-api>=1.15.0,<2
Requires-Dist: opentelemetry-sdk>=1.15.0,<2
Requires-Dist: opentelemetry-exporter-otlp-proto-grpc>=1.15.0,<2
Requires-Dist: opentelemetry-instrumentation-requests>=0.36b0,<1
Requires-Dist: opentelemetry-instrumentation-sqlalchemy>=0.36b0,<1
Requires-Dist: pytest~=6.2.5 ; extra == "test"
Requires-Dist: pytest-html~=2.1.1 ; extra == "test"
Requires-Dist: pre-commit==2.15.0 ; extra == "test"
Project-URL: Home, https://github.com/Form-Energy/formenergy-observability
Provides-Extra: test
